{"best_objective":8927.97971875,"instance":"21-28-3-1.json","voyages":{"PSV_1":{"sequence":[16,24,13,19,26,17,7,0,5],"time_points":{"16":{"service_time":87,"arrival_time":87,"end_time":91},"0":{"service_time":151,"arrival_time":151,"end_time":164},"SD":{"end_time":63},"17":{"service_time":124,"arrival_time":124,"end_time":127},"19":{"service_time":114,"arrival_time":114,"end_time":116},"5":{"service_time":164,"arrival_time":164,"end_time":179},"7":{"service_time":139,"arrival_time":139,"end_time":150},"24":{"service_time":91,"arrival_time":91,"end_time":92},"26":{"service_time":116,"arrival_time":116,"end_time":117},"13":{"service_time":98,"arrival_time":98,"end_time":102},"ED":{"end_time":191}}},"PSV_3":{"sequence":[1,23,12,18,20,21,4],"time_points":{"SD":{"end_time":63},"1":{"service_time":92,"arrival_time":92,"end_time":110},"18":{"service_time":133,"arrival_time":133,"end_time":139},"20":{"service_time":142,"arrival_time":142,"end_time":146},"4":{"service_time":150,"arrival_time":150,"end_time":156},"21":{"service_time":146,"arrival_time":146,"end_time":147},"23":{"service_time":110,"arrival_time":110,"end_time":111},"12":{"service_time":115,"arrival_time":115,"end_time":133},"ED":{"end_time":183}}},"SPOT":{"sequence":[14,27,6,8,25,9],"time_points":{"SD":{"end_time":63},"5":{"service_time":75,"arrival_time":75,"end_time":90},"9":{"service_time":128,"arrival_time":128,"end_time":144},"10":{"service_time":155,"arrival_time":155,"end_time":165},"11":{"service_time":104,"arrival_time":104,"end_time":113},"ED":{"end_time":189}}},"PSV_2":{"sequence":[3,10,22,15,11,2],"time_points":{"SD":{"end_time":63},"2":{"service_time":146,"arrival_time":146,"end_time":155},"3":{"service_time":87,"arrival_time":87,"end_time":95},"22":{"service_time":114,"arrival_time":114,"end_time":115},"10":{"service_time":104,"arrival_time":104,"end_time":114},"11":{"service_time":124,"arrival_time":124,"end_time":133},"15":{"service_time":120,"arrival_time":120,"end_time":123},"ED":{"end_time":168}}}}}