{"best_objective":5030.261319444446,"instance":"17-23-3-1.json","voyages":{"SPOT":{"sequence":[],"time_points":{}},"PSV_3":{"sequence":[4,12,19],"time_points":{"SD":{"end_time":63},"19":{"service_time":95,"arrival_time":95,"end_time":96},"4":{"service_time":75,"arrival_time":75,"end_time":82},"12":{"service_time":87,"arrival_time":87,"end_time":95},"ED":{"end_time":108}}},"PSV_1":{"sequence":[7,3,18,14,0,16,10,11],"time_points":{"0":{"service_time":111,"arrival_time":111,"end_time":129},"16":{"service_time":141,"arrival_time":141,"end_time":147},"SD":{"end_time":63},"18":{"service_time":98,"arrival_time":98,"end_time":99},"3":{"service_time":93,"arrival_time":93,"end_time":98},"7":{"service_time":75,"arrival_time":75,"end_time":81},"10":{"service_time":150,"arrival_time":150,"end_time":158},"11":{"service_time":161,"arrival_time":161,"end_time":165},"14":{"service_time":104,"arrival_time":104,"end_time":110},"ED":{"end_time":195}}},"PSV_2":{"sequence":[8,17,1,6,21,15,2,5,13,22,9,20],"time_points":{"SD":{"end_time":63},"17":{"service_time":142,"arrival_time":142,"end_time":143},"18":{"service_time":125,"arrival_time":125,"end_time":126},"19":{"service_time":83,"arrival_time":83,"end_time":84},"3":{"service_time":120,"arrival_time":120,"end_time":125},"20":{"service_time":110,"arrival_time":110,"end_time":111},"22":{"service_time":102,"arrival_time":102,"end_time":103},"8":{"service_time":131,"arrival_time":131,"end_time":142},"12":{"service_time":75,"arrival_time":75,"end_time":83},"13":{"service_time":96,"arrival_time":96,"end_time":102},"ED":{"end_time":164}}}}}