{"best_objective":4029.1272222222233,"avg_improvement_local_search":0.009711153702019098,"best_improvement_local_search":0.14869297462386402,"instance":"13-18-2-1.json","number_of_iterations":5000,"best_objective_fuel_costs":4029.1272222222237,"number_of_improvements_by_destroy_repair":1,"number_of_local_search_runs":4779,"construction_heuristic_objective":5055.371250000001,"best_solution_found_by":"destroy_repair","heuristic_to_iteration_to_weight":{"regret_insertion":{"0":0.2},"related_removal":{"0":0.2},"worst_removal":{"0":0.2},"spot_removal":{"0":0.2},"cluster_removal":{"0":0.2},"max_order_size_insertion":{"0":0.2},"spread_removal":{"0":0.2},"random_removal":{"0":0.2},"max_penalty_cost_insertion":{"0":0.2},"greedy_insertion":{"0":0.2}},"runtime":124.192597959,"heuristic_to_selections":{"regret_insertion":1276,"related_removal":857,"worst_removal":1001,"spot_removal":695,"cluster_removal":859,"max_order_size_insertion":1196,"spread_removal":779,"random_removal":809,"max_penalty_cost_insertion":1318,"greedy_insertion":1210},"best_objective_penalty_costs":0.0,"iteration_to_objective":{"0":4620.797430555556},"best_sol_found_in_iteration":34,"number_of_improvements_by_set_partitioning":0,"number_of_improvements_by_local_search":3,"number_of_improvements_by_local_search_operators":{"two_exchange":483,"two_relocate":759,"voyage_exchange":756,"one_relocate":1121,"postpone_scheduled":0,"schedule_postponed":3,"one_exchange":615},"parameters":{"reaction":0.1,"cache_size":1000000,"local_search":true,"new_local_score":9.0,"pool_size":100000,"removal_upper_percentage":0.5,"cooling_rate":0.9987578504874692,"removal_lower_percentage":0.15,"regret_k":3,"set_partitioning":true,"local_search_condition":0.2,"lower_weight_threshold":0.2,"segment_iterations":50,"start_temperature":364.66795161138253,"new_solution_score":1.0,"max_iterations_solution":20,"determinism":7.0,"noise_control":0.025,"new_global_score":33.0,"predetermined_iterations":5000}}