{"best_objective":8721.088329861113,"instance":"27-32-5-1.json","voyages":{"PSV_2":{"sequence":[24,5,13,28,2,0,29,16],"time_points":{"0":{"service_time":135,"arrival_time":135,"end_time":145},"16":{"service_time":147,"arrival_time":147,"end_time":153},"SD":{"end_time":63},"2":{"service_time":112,"arrival_time":112,"end_time":128},"5":{"service_time":91,"arrival_time":91,"end_time":98},"24":{"service_time":75,"arrival_time":75,"end_time":80},"28":{"service_time":109,"arrival_time":109,"end_time":110},"13":{"service_time":98,"arrival_time":98,"end_time":109},"29":{"service_time":145,"arrival_time":145,"end_time":146},"ED":{"end_time":166}}},"PSV_4":{"sequence":[21,10],"time_points":{"SD":{"end_time":63},"21":{"service_time":73,"arrival_time":73,"end_time":78},"10":{"service_time":79,"arrival_time":79,"end_time":95},"ED":{"end_time":107}}},"PSV_1":{"sequence":[19,7,9,11,4],"time_points":{"SD":{"end_time":63},"19":{"service_time":92,"arrival_time":92,"end_time":102},"4":{"service_time":153,"arrival_time":153,"end_time":162},"7":{"service_time":102,"arrival_time":102,"end_time":111},"9":{"service_time":114,"arrival_time":114,"end_time":120},"11":{"service_time":121,"arrival_time":121,"end_time":140},"ED":{"end_time":175}}},"PSV_5":{"sequence":[3,27,20,23,12,22,8,17,31,26],"time_points":{"SD":{"end_time":63},"17":{"service_time":155,"arrival_time":155,"end_time":159},"3":{"service_time":93,"arrival_time":93,"end_time":98},"20":{"service_time":106,"arrival_time":106,"end_time":110},"22":{"service_time":137,"arrival_time":137,"end_time":142},"23":{"service_time":112,"arrival_time":112,"end_time":117},"8":{"service_time":144,"arrival_time":144,"end_time":155},"26":{"service_time":169,"arrival_time":169,"end_time":170},"27":{"service_time":98,"arrival_time":98,"end_time":99},"12":{"service_time":117,"arrival_time":117,"end_time":135},"31":{"service_time":159,"arrival_time":159,"end_time":160},"ED":{"end_time":182}}},"PSV_3":{"sequence":[18,14,15,6,1,30,25],"time_points":{"SD":{"end_time":63},"1":{"service_time":138,"arrival_time":138,"end_time":148},"18":{"service_time":76,"arrival_time":76,"end_time":82},"6":{"service_time":132,"arrival_time":132,"end_time":138},"25":{"service_time":156,"arrival_time":156,"end_time":157},"14":{"service_time":99,"arrival_time":99,"end_time":112},"30":{"service_time":148,"arrival_time":148,"end_time":149},"15":{"service_time":115,"arrival_time":115,"end_time":132},"ED":{"end_time":184}}},"SPOT":{"sequence":[],"time_points":{}}}}