{
  "instance_info": {
    "fleet_size": 2,
    "installation_ordering": "random",
    "number_of_installations": 15,
    "order_composition": {
      "1": {
        "installation": 22,
        "node": 1,
        "order": "(O0-MD-I22)",
        "size": 29
      },
      "2": {
        "installation": 16,
        "node": 2,
        "order": "(O1-MD-I16)",
        "size": 27
      },
      "3": {
        "installation": 8,
        "node": 3,
        "order": "(O2-MD-I8)",
        "size": 40
      },
      "4": {
        "installation": 24,
        "node": 4,
        "order": "(O3-MD-I24)",
        "size": 12
      },
      "5": {
        "installation": 27,
        "node": 5,
        "order": "(O4-MD-I27)",
        "size": 31
      },
      "6": {
        "installation": 18,
        "node": 6,
        "order": "(O5-MD-I18)",
        "size": 21
      },
      "7": {
        "installation": 7,
        "node": 7,
        "order": "(O6-MD-I7)",
        "size": 24
      },
      "8": {
        "installation": 4,
        "node": 8,
        "order": "(O7-MD-I4)",
        "size": 23
      },
      "9": {
        "installation": 1,
        "node": 9,
        "order": "(O8-MD-I1)",
        "size": 24
      },
      "10": {
        "installation": 25,
        "node": 10,
        "order": "(O9-MD-I25)",
        "size": 29
      },
      "11": {
        "installation": 20,
        "node": 11,
        "order": "(O10-MD-I20)",
        "size": 24
      },
      "12": {
        "installation": 9,
        "node": 12,
        "order": "(O11-OD-I9)",
        "size": 4
      },
      "13": {
        "installation": 17,
        "node": 13,
        "order": "(O12-OD-I17)",
        "size": 15
      },
      "14": {
        "installation": 15,
        "node": 14,
        "order": "(O13-OD-I15)",
        "size": 10
      },
      "15": {
        "installation": 11,
        "node": 15,
        "order": "(O14-OP-I11)",
        "size": 19
      },
      "16": {
        "installation": 25,
        "node": 16,
        "order": "(O15-OP-I25)",
        "size": 12
      },
      "17": {
        "installation": 8,
        "node": 17,
        "order": "(O16-OP-I8)",
        "size": 39
      }
    },
    "weather_scenario": "perfect"
  },
  "objective": {
    "charter_costs": 1064.0,
    "fuel_costs": 5845.1657,
    "objective_bound": 8241.3498,
    "optimality_gap": 0.2999886314373764,
    "penalty_costs": 0.0,
    "incumbent": 11773.1657
  },
  "order_fulfillment": {
    "postponed_orders": [],
    "serviced_orders": [
      1,
      2,
      3,
      4,
      5,
      6,
      7,
      8,
      9,
      10,
      11,
      12,
      13,
      14,
      15,
      16,
      17
    ]
  },
  "runtime": {
    "model_runtime": 600.0461,
    "preprocess_runtime": 24.3949
  },
  "variables": {
    "number_of_arcs": 571881,
    "number_of_bin_variables": 571938,
    "number_of_cont_variables": 114,
    "number_of_variables": 572052
  },
  "vessels": {
    "chartered_vessels": 1,
    "fleet_vessels": 2
  },
  "voyages": {
    "0": {
      "0": [
        2,
        [
          63,
          90,
          101
        ],
        10.0,
        [
          129.0,
          0
        ],
        [
          711.2175000000002,
          0.0
        ]
      ],
      "2": [
        14,
        [
          101,
          102,
          106
        ],
        10.0,
        [
          102.0,
          0
        ],
        [
          68.48250000000002,
          0.0
        ]
      ],
      "3": [
        17,
        [
          146,
          146,
          147
        ],
        0,
        [
          28.0,
          0
        ],
        [
          11.73,
          0.0
        ]
      ],
      "9": [
        18,
        [
          174,
          186,
          186
        ],
        10.0,
        [
          0,
          131.0
        ],
        [
          258.75000000000006,
          0.0
        ]
      ],
      "11": [
        3,
        [
          121,
          130,
          146
        ],
        10.0,
        [
          68.0,
          0
        ],
        [
          381.74250000000006,
          0.0
        ]
      ],
      "12": [
        15,
        [
          149,
          154,
          155
        ],
        10.0,
        [
          24.0,
          39.0
        ],
        [
          119.54250000000005,
          0.0
        ]
      ],
      "14": [
        11,
        [
          106,
          111,
          121
        ],
        10.0,
        [
          92.0,
          0
        ],
        [
          225.11250000000007,
          0.0
        ]
      ],
      "15": [
        9,
        [
          155,
          164,
          174
        ],
        10.0,
        [
          24.0,
          92.99999999999997
        ],
        [
          311.36250000000007,
          0.0
        ]
      ],
      "17": [
        12,
        [
          147,
          147,
          149
        ],
        0,
        [
          28.0,
          39.0
        ],
        [
          23.46,
          0.0
        ]
      ]
    },
    "1": {
      "0": [
        8,
        [
          63,
          76,
          86
        ],
        10.0,
        [
          129.0,
          0
        ],
        [
          439.1402777777779,
          0.0
        ]
      ],
      "1": [
        10,
        [
          136,
          140,
          152
        ],
        10.0,
        [
          41.0,
          0
        ],
        [
          239.78777777777782,
          0.0
        ]
      ],
      "4": [
        18,
        [
          158,
          188,
          188
        ],
        10.0,
        [
          0,
          130.0
        ],
        [
          742.7083333333335,
          0.0
        ]
      ],
      "6": [
        13,
        [
          103,
          111,
          117
        ],
        10.0,
        [
          85.0,
          0
        ],
        [
          268.4355555555556,
          0.0
        ]
      ],
      "8": [
        6,
        [
          86,
          94,
          103
        ],
        10.0,
        [
          106.0,
          0
        ],
        [
          303.6255555555556,
          0.0
        ]
      ],
      "10": [
        16,
        [
          152,
          152,
          153
        ],
        0,
        [
          12.0,
          0
        ],
        [
          11.73,
          0.0
        ]
      ],
      "13": [
        1,
        [
          117,
          124,
          136
        ],
        10.0,
        [
          70.0,
          0
        ],
        [
          314.0586111111112,
          0.0
        ]
      ],
      "16": [
        4,
        [
          153,
          153,
          158
        ],
        10.0,
        [
          12.0,
          12.0
        ],
        [
          58.650000000000006,
          0.0
        ]
      ]
    },
    "2": {
      "0": [
        7,
        [
          63,
          71,
          81
        ],
        13.999999999999998,
        [
          55.0,
          0
        ],
        [
          682.6783333333331,
          2736.0
        ]
      ],
      "5": [
        18,
        [
          95,
          102,
          102
        ],
        14.0,
        [
          0,
          0
        ],
        [
          494.7060416666668,
          1064.0
        ]
      ],
      "7": [
        5,
        [
          81,
          82,
          95
        ],
        10.0,
        [
          31.0,
          0
        ],
        [
          178.24520833333335,
          2128.0
        ]
      ]
    }
  }
}